otary/__init__.py
otary/geometry/__init__.py
otary/geometry/continuous/__init__.py
otary/geometry/continuous/entity.py
otary/geometry/continuous/shape/__init__.py
otary/geometry/continuous/shape/circle.py
otary/geometry/continuous/shape/ellipse.py
otary/geometry/discrete/__init__.py
otary/geometry/discrete/entity.py
otary/geometry/discrete/linear/__init__.py
otary/geometry/discrete/linear/directed/__init__.py
otary/geometry/discrete/linear/directed/entity.py
otary/geometry/discrete/linear/directed/utils/direction.py
otary/geometry/discrete/linear/directed/vector.py
otary/geometry/discrete/linear/directed/vectorized_linear_spline.py
otary/geometry/discrete/linear/entity.py
otary/geometry/discrete/linear/linear_spline.py
otary/geometry/discrete/linear/segment.py
otary/geometry/discrete/point.py
otary/geometry/discrete/shape/__init__.py
otary/geometry/discrete/shape/axis_aligned_rectangle.py
otary/geometry/discrete/shape/polygon.py
otary/geometry/discrete/shape/rectangle.py
otary/geometry/discrete/shape/triangle.py
otary/geometry/entity.py
otary/geometry/utils/__init__.py
otary/geometry/utils/constants.py
otary/geometry/utils/tools.py
otary/image/__init__.py
otary/image/base.py
otary/image/components/__init__.py
otary/image/components/drawer/__init__.py
otary/image/components/drawer/drawer.py
otary/image/components/drawer/utils/__init__.py
otary/image/components/drawer/utils/render.py
otary/image/components/drawer/utils/tools.py
otary/image/components/io/__init__.py
otary/image/components/io/reader.py
otary/image/components/io/utils/readfile.py
otary/image/components/io/writer.py
otary/image/components/transformer/__init__.py
otary/image/components/transformer/components/__init__.py
otary/image/components/transformer/components/binarizer/__init__.py
otary/image/components/transformer/components/binarizer/binarizer.py
otary/image/components/transformer/components/binarizer/ops/__init__.py
otary/image/components/transformer/components/binarizer/ops/adotsu.py
otary-0.4.0.dist-info/METADATA
otary-0.4.0.dist-info/WHEEL
otary-0.4.0.dist-info/licenses/LICENSE
otary-0.4.0.dist-info/RECORD
