Metadata-Version: 2.4
Name: otary
Version: 0.4.0
Summary: Otary — elegant, readable, and powerful image and 2D geometry Python library.
License-File: LICENSE
Author: Alexandre Poupeau
Author-email: alexandre.poupeau.contact@gmail.com
Requires-Python: >=3.10,<4.0
Classifier: Programming Language :: Python :: 3
Classifier: Programming Language :: Python :: 3.10
Classifier: Programming Language :: Python :: 3.11
Classifier: Programming Language :: Python :: 3.12
Classifier: Programming Language :: Python :: 3.13
Classifier: Programming Language :: Python :: 3.14
Requires-Dist: opencv-python (>=4.10.0.84,<5.0.0.0)
Requires-Dist: pillow (>=11.3.0,<12.0.0)
Requires-Dist: pymupdf (>=1.24.12,<2.0.0)
Requires-Dist: shapely (>=2.0.4,<3.0.0)
